{
  "timestamp": "2022-11-14T11:19:21",
  "url": "https://www.gmx.net/magazine/",
  "response": {
    "status": 200
  },
  "scripts": [
    {
      "type": "module",
      "src": "https://s.uicdn.com/uimag/5.1182.0/assets/_sn_/lod/social.js",
      "id": null,
      "text": null
    },
    {
      "type": "module",
      "src": "https://s.uicdn.com/uimag/5.1182.0/assets/_sn_/lod/multisearch.js",
      "id": null,
      "text": null
    },
    {
      "type": "module",
      "src": "https://s.uicdn.com/uimag/5.1182.0/assets/_sn_/lod/navigation.js",
      "id": null,
      "text": null
    },
    {
      "type": "module",
      "src": "https://s.uicdn.com/uimag/5.1182.0/assets/_sn_/lod/entry.js",
      "id": null,
      "text": null
    },
    {
      "type": "module",
      "src": "https://s.uicdn.com/uimag/5.1182.0/assets/_sn_/lod/starpreview.js",
      "id": null,
      "text": null
    }
  ],
  "articles": [
    {
      "title": "Wolodymyr Selenskyj reist in befreites Cherson – Russland zeigt sich erbost",
      "url": "https://www.gmx.net/magazine/politik/russland-krieg-ukraine/ukraine-krieg-live-ticker-wolodymyr-selenskyj-reist-befreites-cherson-russland-zeigt-erbost-37469008",
      "image_url": "https://i0.gmx.net/image/498/37469498,pd=4,f=responsive169-w950/ukraine-krieg-selenskyj-cherson.jpg"
    },
    {
      "title": "Putins Chefdiplomat Lawrow in Krankenhaus eingeliefert? Russland dementiert",
      "url": "https://www.gmx.net/magazine/politik/putins-chefdiplomat-lawrow-krankenhaus-eingeliefert-russland-dementiert-37469200",
      "image_url": "https://i0.gmx.net/image/186/37469186,pd=4,f=responsive169-w450.jpg"
    },
    {
      "title": "Musk liefert sich Schlagabtausch mit US-Senator nach Fake-Account-Chaos",
      "url": "https://www.gmx.net/magazine/politik/musk-streit-us-senator-fake-account-chaos-37469078",
      "image_url": "https://i0.gmx.net/image/080/37469080,pd=2,f=responsive169-w450/elon-musk.jpg"
    },
    {
      "title": "Bundesrat beschließt Entlastung für Gaskunden",
      "url": "https://www.gmx.net/magazine/politik/bundesrat-beschliesst-entlastung-gaskunden-37469410",
      "image_url": "https://i0.gmx.net/image/412/37469412,pd=2,f=responsive169-w450/gaszaehler.jpg"
    },
    {
      "title": "EU beschließt erneut Sanktionen gegen den Iran",
      "url": "https://www.gmx.net/magazine/politik/eu-beschliesst-sanktionen-iran-37469286",
      "image_url": "https://i0.gmx.net/image/262/37469262,pd=1,f=responsive169-w450/proteste-iran.jpg"
    },
    {
      "title": "Gipfel vor dem Gipfel: Treffen von Biden und Xi von vielen Streitthemen belastet",
      "url": "https://www.gmx.net/magazine/politik/gipfel-gipfel-treffen-biden-xi-streitthemen-belastet-37469094",
      "image_url": "https://i0.gmx.net/image/154/37469154,pd=1,f=responsive169-w450.jpg"
    },
    {
      "title": "Türkei macht PKK-Anhängerin aus Syrien für Anschlag in Istanbul verantwortlich",
      "url": "https://www.gmx.net/magazine/politik/tuerkei-erdogan/tuerkei-pkk-anhaengerin-syrien-anschlag-istanbul-verantwortlich-37469162",
      "image_url": "https://i0.gmx.net/image/164/37469164,pd=2,f=responsive169-w450/explosion-istanbul-tote-verletzte.jpg"
    },
    {
      "title": "Was macht Donald Trumps Lieblingstochter Ivanka eigentlich heute?",
      "url": "https://www.gmx.net/magazine/politik/us-politik/ivanka-trump-37469062",
      "image_url": "https://i0.gmx.net/image/064/37469064,pd=2,f=responsive169-w450/ivanka-trump.jpg"
    },
    {
      "title": "Leonardo DiCaprio feiert stargespickte Geburtstagsparty - ohne Gigi Hadid?",
      "url": "https://www.gmx.net/magazine/unterhaltung/stars/leonardo-dicaprio-feiert-stargespickte-geburtstagsparty-37469386",
      "image_url": "https://i0.gmx.net/image/288/37469288,pd=2,f=responsive169-w450/leonardo-dicaprio.jpg"
    },
    {
      "title": "Schon acht OPs: Wilfried Gliem berichtet von monatelanger Krankenhaus-Odyssee",
      "url": "https://www.gmx.net/magazine/unterhaltung/musik/schlager/wilfried-gliem-monatelanger-krankenhaus-odyssee-37469172",
      "image_url": "https://i0.gmx.net/image/174/37469174,pd=1,f=responsive169-w450/wilfried-gliem.jpg"
    },
    {
      "title": "Sie ziehen in den Container: \"Promi Big Brother\" gibt weitere Kandidaten bekannt",
      "url": "https://www.gmx.net/magazine/unterhaltung/tv-shows/promi-big-brother/jay-khan-promi-big-brother-kandidaten-37469112",
      "image_url": "https://i0.gmx.net/image/134/37469134,pd=2,f=responsive169-w450/tanja-tischewitsch-joerg-dahlmann-sam-dylan-jay-kh.jpg"
    },
    {
      "title": "Laura Winter und Jonas Hofmann haben sich verlobt",
      "url": "https://www.gmx.net/magazine/unterhaltung/stars/moderatorin-laura-winter-nationalspieler-jonas-hofmann-verlobung-geburtstag-37468494",
      "image_url": "https://i0.gmx.net/image/502/37468502,pd=1,f=responsive169-w450/laura-winter-jonas-hofmann.jpg"
    },
    {
      "title": "Vorurteil im Check: Machen kalte Füße tatsächlich krank?",
      "url": "https://www.gmx.net/magazine/unterhaltung/vorurteil-vs-echtes-risiko-kalte-fuesse-krank-37469348",
      "image_url": "https://i0.gmx.net/image/350/37469350,pd=2,f=responsive169-w450/dran-kalte-fuesse-krank.jpg"
    },
    {
      "title": "Inflation verändert Konsumverhalten: Daran sparen die Deutschen hauptsächlich",
      "url": "https://www.gmx.net/magazine/ratgeber/finanzen-verbraucher/umfrage-ergibt-deutsche-sparen-restaurantbesuchen-37468926",
      "image_url": "https://i0.gmx.net/image/056/37469056,pd=1,f=responsive169-w450/kassenbon.jpg"
    },
    {
      "title": "Kolumbien! Oder Venezuela? Dieses Flaggen-Quiz ist nichts für Anfänger",
      "url": "https://www.gmx.net/magazine/reise/gut-kennen-flaggen-nord-suedamerikas-36585618",
      "image_url": "https://i0.gmx.net/image/404/36585404,pd=1,f=responsive169-w450/amerika-flaggen-quiz-raten.jpg"
    },
    {
      "title": "Reaktor steht still: Mediziner fürchten Versorgungsengpässe für Krebspatienten",
      "url": "https://www.gmx.net/magazine/gesundheit/reaktor-still-mediziner-fuerchten-versorgungsengpaesse-krebspatienten-37467224",
      "image_url": "https://i0.gmx.net/image/270/37467270,pd=2,f=responsive169-w450.jpg"
    },
    {
      "title": "Grippewelle führt Praxen an Belastungsgrenze: Ärzte geben wichtigen Rat",
      "url": "https://www.gmx.net/magazine/gesundheit/hausaerzte-kliniken-warnen-belastungen-grippewelle-37467120",
      "image_url": "https://i0.gmx.net/image/892/37458892,pd=2,f=responsive169-w450/illustration-grippe.jpg"
    },
    {
      "title": "\"Ziemlich ergreifend\": Totale Euphorie bei NFL-Premiere in München",
      "url": "https://www.gmx.net/magazine/sport/nfl/ziemlich-ergreifend-totale-euphorie-nfl-premiere-muenchen-37469100",
      "image_url": "https://i0.gmx.net/image/102/37469102,pd=2,f=responsive169-w450/muenchen-football-fieber.jpg"
    },
    {
      "title": "Eine Trainer-Legende beendet ihre erfolgreiche Karriere",
      "url": "https://www.gmx.net/magazine/sport/fussball/international/trainer-legende-luiz-felipe-scolari-hoert-37469042",
      "image_url": "https://i0.gmx.net/image/066/37469066,pd=1,f=responsive169-w450/brasiliens-trainer-legende-luiz-felipe-scolari-wec.jpg"
    },
    {
      "title": "\"Das Beste, was es gibt\": NFL-Superstar Brady schwärmt von Spiel in München",
      "url": "https://www.gmx.net/magazine/sport/nfl/beste-nfl-superstar-brady-schwaermt-spiel-muenchen-37469052",
      "image_url": "https://i0.gmx.net/image/054/37469054,pd=2,f=responsive169-w450/tampa-bay-buccaneers-seattle-seahawks.jpg"
    },
    {
      "title": "Die große Ronaldo-Abrechnung",
      "url": "https://www.gmx.net/magazine/sport/fussball/international/cristiano-ronaldo-brisantes-interview-rechnet-trainer-erik-ten-hag-37468762",
      "image_url": "https://i0.gmx.net/image/764/37468764,pd=3,f=responsive169-w450/cristiano-ronaldo.jpg"
    },
    {
      "title": "Verstappen verweigert Perez Hilfe: \"Das zeigt, wer er wirklich ist\"",
      "url": "https://www.gmx.net/magazine/sport/formel-1/formel-1-zoff-red-bull-verstappen-verweigert-perez-hilfe-zeigt-37468544",
      "image_url": "https://i0.gmx.net/image/546/37468546,pd=2,f=responsive169-w450/sergio-perez-max-verstappen.jpg"
    },
    {
      "title": "Orchidee nach dem Kanzler benannt: \"Renanthera Olaf Scholz\"",
      "url": "https://www.gmx.net/magazine/wissen/natur-umwelt/orchidee-kanzler-benannt-renanthera-olaf-scholz-37469124",
      "image_url": "https://i0.gmx.net/image/126/37469126,pd=2,f=responsive169-w450/bundeskanzler-olaf-scholz-spd-reist-asien.jpg"
    },
    {
      "title": "\"Großes Sicherheitsrisiko\": ADAC warnt vor Lkw-Falschparkern an Raststätten",
      "url": "https://www.gmx.net/magazine/auto/hohes-risiko-lkw-falschparker-adac-autobahn-raststaetten-regel-37454154",
      "image_url": "https://i0.gmx.net/image/156/37454156,pd=1,f=responsive169-w450/lastwagen-rastplatz.jpg"
    },
    {
      "title": "Optische Täuschung: Ist das die gleiche Szene aus zwei Perspektiven?",
      "url": "https://www.gmx.net/magazine/wissen/wissenschaft-technik/optische-taeuschung-gleiche-szene-perspektiven-37464890",
      "image_url": "https://i0.gmx.net/image/892/37464892,pd=2,f=responsive169-w450/optische-taeuschung-gleiche-szene-perspektiven.jpg"
    },
    {
      "title": "Gigantisch und stark umstritten: Das Bauprojekt \"Neom\" in Saudi-Arabien",
      "url": "https://www.gmx.net/magazine/wissen/wissenschaft-technik/gigantisch-umstritten-bauprojekt-neom-saudi-arabien-37452508",
      "image_url": "https://i0.gmx.net/image/532/37452532,pd=3,f=responsive169-w450.jpg"
    },
    {
      "title": "Zu gefährlich? Wann Sport nach COVID-Infektion wieder möglich ist",
      "url": "https://www.gmx.net/magazine/gesundheit/vorgehen-corona-infektion-sport-treiben-37452048",
      "image_url": "https://i0.gmx.net/image/052/37452052,pd=2,f=responsive169-w450.jpg"
    },
    {
      "title": "Russlands Angriff auf die Ukraine (ständig aktualisiert)",
      "url": "https://www.gmx.net/magazine/infografiken/russlands-angriff-ukraine-staendig-aktualisiert-36683098",
      "image_url": "https://i0.gmx.net/image/508/36794508,pd=37,f=responsive169-w450.jpg"
    },
    {
      "title": "Mutationen können für Viren vorteilhaft sein",
      "url": "https://www.gmx.net/magazine/infografiken/mutationen-viren-vorteilhaft-36682050",
      "image_url": "https://i0.gmx.net/image/208/36381208,pd=2,f=responsive169-w450.jpg"
    },
    {
      "title": "Übersicht: Die 23 Rennen der Formel-1-WM 2022",
      "url": "https://www.gmx.net/magazine/infografiken/uebersicht-23-rennen-formel-1-wm-2022-36682022",
      "image_url": "https://i0.gmx.net/image/612/36671612,pd=4,f=responsive169-w450/f1-saison-2022-weltkarte-23-rennen.png"
    },
    {
      "title": "Russischer Einmarsch in die Ukraine",
      "url": "https://www.gmx.net/magazine/infografiken/russischer-einmarsch-ukraine-36681988",
      "image_url": "https://i0.gmx.net/image/516/36637516,pd=2,f=responsive169-w450/russlands-krieg-ukraine.jpg"
    },
    {
      "title": "Das ukrainische Atomkraftwerk Saporischschja",
      "url": "https://www.gmx.net/magazine/infografiken/ukrainische-atomkraftwerk-saporischschja-36681956",
      "image_url": "https://i0.gmx.net/image/664/36662664,pd=2,f=responsive169-w450.jpg"
    },
    {
      "title": "UNICEF: Immer mehr Kinder leiden unter Hitzewellen",
      "url": "https://www.gmx.net/magazine/unicef/unicef-kinder-leiden-hitzewellen-37414636",
      "image_url": "https://i0.gmx.net/image/646/37414646,pd=2,f=responsive169-w450/duerre-sambia.jpg"
    },
    {
      "title": "Mit einer UNICEF-Patenschaft helfen Sie Kindern in Not",
      "url": "https://wa.gmx.net/gmx/gmx/s?name=themen.startpage.clickout.startpage.30018492&partner=undef&country=de&type=clickout&destpartner=undef&click1=30018492&click2=content&click3=teaserset_9&click4=3&_u=http://bit.ly/UI-Helfen-Gmx&_hs=d4c40fbc47275998fc217d18a04b4419",
      "image_url": "https://i0.gmx.net/image/216/34085216,pd=3,f=responsive169-w450/unicef-adut-suedsudan.jpg"
    },
    {
      "title": "Rückschläge bei der Gesundheit von Frauen und Kindern",
      "url": "https://www.gmx.net/magazine/unicef/un-bericht-rueckschlaege-gesundheit-frauen-kindern-37392916",
      "image_url": "https://i0.gmx.net/image/176/37393176,pd=2,f=responsive169-w450/saeugling-medizinisch-untersucht.jpg"
    },
    {
      "title": "UNICEF-Studie: Vier Millionen Kinder in Armut geraten",
      "url": "https://www.gmx.net/magazine/unicef/unicef-studie-millionen-kinder-zusaetzlich-armut-geraten-37392564",
      "image_url": "https://i0.gmx.net/image/702/37392702,pd=2,f=responsive169-w450/ukrainisches-maedchen-polen.jpg"
    },
    {
      "title": "Globale Krisen verschärfen dramatische Ernährungslage",
      "url": "https://www.gmx.net/magazine/unicef/welthunger-index-globale-krisen-verschaerfen-dramatische-lage-37382874",
      "image_url": "https://i0.gmx.net/image/900/37382900,pd=3,f=responsive169-w450/oberarmmessung-mangelernaehrtem-kind-haiti.jpg"
    },
    {
      "title": "UNICEF: Elf wichtige Fakten über Mädchen",
      "url": "https://www.gmx.net/magazine/unicef/weltmaedchentag-wichtige-fakten-maedchen-32573006",
      "image_url": "https://i0.gmx.net/image/592/37371592,pd=2,f=responsive169-w450/maedchen-ueberschwemmungen-pakistan.jpg"
    }
  ]
}