{
  "timestamp": "2022-06-27T13:46:24",
  "url": "https://www.bild.de/geld/startseite/geld/geld-15683376.bild.html",
  "response": {
    "status": 200
  },
  "scripts": [
    {
      "type": null,
      "src": "https://player.h-cdn.com/loader.js?customer=bild",
      "id": null,
      "text": null
    },
    {
      "type": null,
      "src": "https://cmp2.bild.de/wrapperMessagingWithoutDetection.js",
      "id": null,
      "text": null
    },
    {
      "type": null,
      "src": "https://www.asadcdn.com/adlib/pages/bild.js",
      "id": null,
      "text": null
    },
    {
      "type": null,
      "src": "https://rosetta.prod.ps.bild.de/ps-rosetta.js",
      "id": null,
      "text": null
    },
    {
      "type": null,
      "src": "https://tags.tiqcdn.com/utag/axelspringer/bild-bild.de/prod/utag.js",
      "id": null,
      "text": null
    },
    {
      "type": null,
      "src": "https://data-bb21a2f11b.bild.de/iomm/latest/bootstrap/loader.js",
      "id": null,
      "text": null
    },
    {
      "type": null,
      "src": "https://a.bildstatic.de/runtime.7b175359.js",
      "id": null,
      "text": null
    },
    {
      "type": null,
      "src": "https://a.bildstatic.de/pages/_.535feb38.js",
      "id": null,
      "text": null
    },
    {
      "type": null,
      "src": "https://a.bildstatic.de/vendors/pages/_.695ea104.js",
      "id": null,
      "text": null
    },
    {
      "type": null,
      "src": "https://a.bildstatic.de/commons/app.f7c2cdf1.js",
      "id": null,
      "text": null
    },
    {
      "type": null,
      "src": "https://a.bildstatic.de/vendors/app.7abfe18e.js",
      "id": null,
      "text": null
    },
    {
      "type": null,
      "src": "https://a.bildstatic.de/app.fddc9598.js",
      "id": null,
      "text": null
    }
  ],
  "articles": [
    {
      "title": "Deutsche Börse : Kurserholung beim Dax setzt sich fort",
      "url": "https://www.bild.de/geld/wirtschaft/wirtschaft/deutsche-boerse-kurserholung-beim-dax-setzt-sich-fort-80528444.bild.html",
      "image_url": "https://images.bild.de/62b9a5f1e76cc679c115cb90/96fda8f5819d63e856aea4728d6088b0,1013a25e?w=656",
      "image_title": "Deutsche Börse: Kurserholung beim Dax setzt sich fort"
    },
    {
      "title": "Arbeitsmarkt-Experte schlägt Alarm : Wir brauchen 700 000 Einwanderer – pro Jahr!",
      "url": "https://www.bild.de/geld/wirtschaft/wirtschaft/arbeitsmarkt-experte-deutschland-braucht-700000-einwanderer-pro-jahr-80521808.bild.html",
      "image_url": "https://images.bild.de/62b8c4415af3107fc3aa4aec/1772c482c040622189df1fc3964b3efe,21e8fd95?w=320",
      "image_title": "Arbeitsmarkt-Experte: Deutschland braucht 700 000 Einwanderer pro Jahr"
    },
    {
      "title": "Neue Grundsteuer-Regel : Das müssen Hausbesitzer jetzt wissen",
      "url": "https://www.bild.de/bild-plus/geld/mein-geld/kolumne/neue-grundsteuer-regel-das-muessen-hausbesitzer-jetzt-wissen-80511446.bild.html",
      "image_url": "https://images.bild.de/62b7321aa6debe5900c8531c/d22ebce5dd30864864d918c560feb40a,c29e5f59?w=320",
      "image_title": "Neue Grundsteuer-Regel: Das müssen Hausbesitzer jetzt wissen"
    },
    {
      "title": "Ich glaub’, mich knutscht ein Elch Mercedes-Hammer! A-Klasse wird eingestellt",
      "url": "https://www.bild.de/auto/auto-news/wirtschaft/mercedes-a-klasse-wird-um-2025-eingestellt-modell-nicht-rentabel-80522162.bild.html"
    },
    {
      "title": "Teuer-Schock Gas-Kunden drohen bis zu 2000 Euro Mehrkosten!",
      "url": "https://www.bild.de/bild-plus/geld/wirtschaft/wirtschaft/gaspreis-schock-bin-ich-mit-einer-preis-garantie-abgesichert-80505068.bild.html"
    },
    {
      "title": "Habeck befürchtet Kommt der komplette Gas-Stopp?",
      "url": "https://www.bild.de/geld/wirtschaft/wirtschaft/es-wird-auf-jeden-fall-knapp-im-winter-habeck-fuerchtet-russischen-gas-stopp-80497868.bild.html"
    },
    {
      "title": "Musk will ihn wieder „zwitschern“ lassen : Trump-Comeback bei Twitter?",
      "url": "https://www.bild.de/video/clip/video/musk-will-ihn-wieder-zwitschern-lassen-trump-comeback-bei-twitter-80046052,auto=true.bild.html",
      "image_title": "Musk will ihn wieder „zwitschern“ lassen: Trump-Comeback bei Twitter?"
    },
    {
      "title": "Finanzminister Olaf Scholz bei BILD LIVE : „Moralische Verpflichtung, Preise zu senken“",
      "url": "https://www.bild.de/video/clip/politik-inland/finanzminister-olaf-scholz-bei-bild-live-moralische-verpflichtung-preise-zu-senk-71613620-71615334,auto=true.bild.html",
      "image_title": "Finanzminister Olaf Scholz bei BILD LIVE: „Moralische Verpflichtung, Preise zu senken“"
    },
    {
      "title": "Extreme Inflation in Venezuela : Das Geld liegt auf der Straße",
      "url": "https://www.bild.de/video/clip/video/extreme-inflation-in-venezuela-das-geld-liegt-auf-der-strasse-78957952,auto=true.bild.html",
      "image_title": "Extreme Inflation in Venezuela: Das Geld liegt auf der Straße"
    },
    {
      "title": "Was steckt hinter dem Mega-Hype? : Mit diesem Video versteht jeder den Bitcoin-Boom",
      "url": "https://www.bild.de/video/clip/wirtschaft/was-steckt-hinter-dem-mega-hype-mit-diesem-video-versteht-jeder-den-bitcoin-boom-76199578,auto=true.bild.html",
      "image_title": "Blockchain: Mit diesem Video versteht jeder den Bitcoin-Boom"
    },
    {
      "title": "Alarmierende BILD-Umfrage : Nur jeder Vierte legt Geld für Pflege zurück",
      "url": "https://www.bild.de/geld/mein-geld/leben-und-sparen/alarmierende-bild-umfrage-nur-jeder-vierte-legt-geld-fuer-pflege-zurueck-80441130.bild.html",
      "image_title": "Alarmierende BILD-Umfrage: Nur jeder Vierte legt Geld für Pflege zurück"
    },
    {
      "title": "Teuer-Gas : Was, wenn ich es mir nicht mehr leisten kann?",
      "teaser": "Gaspreis-Schock: Was ist, wenn ich es mir nicht mehr leisten kann?",
      "url": "https://www.bild.de/bild-plus/geld/mein-geld/leben-und-sparen/gaspreis-schock-was-wenn-ich-es-mir-nicht-mehr-leisten-kann-80485016.bild.html",
      "image_title": "Gaspreis-Schock: Was, wenn ich es mir nicht mehr leisten kann?"
    },
    {
      "title": "Nach GEZ-Erhöhung : Rekord-Einnahmen für ARD und ZDF",
      "teaser": "Sie bekamen 2021 trotz der Corona-Pandemie 3,8 Prozent mehr Geld – ein neuer Rekord.",
      "url": "https://www.bild.de/geld/wirtschaft/politik-inland/nach-beitragserhoehung-rekord-einnahmen-fuer-ard-und-zdf-80403690.bild.html",
      "image_title": "Nach Beitragserhöhung: Rekord-Einnahmen für ARD und ZDF"
    },
    {
      "title": "Hammer beim Reise-Riesen : Tui-Chef Joussen tritt zurück",
      "teaser": "Der Chef des Reisekonzerns Tui, Fritz Joussen, tritt zurück.",
      "url": "https://www.bild.de/geld/wirtschaft/wirtschaft/tui-chef-hammer-beim-reise-riesen-fritz-joussen-tritt-zurueck-80497616.bild.html",
      "image_title": "Tui: Chef Fritz Joussen tritt beim Reisekonzern zurück"
    },
    {
      "title": "Der Anti-Teuer-Rat von BILD : Schicken Sie uns Ihre Fragen zum Gas-Schock",
      "teaser": "Millionen Haushalte im Gaspreis-Schock: Schicken Sie uns Ihre Fragen.",
      "url": "https://www.bild.de/geld/wirtschaft/wirtschaft/der-anti-teuer-rat-von-bild-schicken-sie-uns-ihre-fragen-zum-gas-schock-80497818.bild.html",
      "image_title": "Der Anti-Teuer-Rat von BILD: Schicken Sie uns Ihre Fragen zum Gas-Schock"
    },
    {
      "title": "Um später krass abzusahnen : Börsen-Millionär: Diese Top-Aktien kaufe ich JETZT",
      "url": "https://www.bild.de/bild-plus/geld/mein-geld/leben-und-sparen/nach-aktien-absturz-verraet-boersen-millionaer-diese-aktien-kaufe-ich-jetzt-80207256.bild.html",
      "image_title": "Nach Korrektur: Börsen-Millionär: Diese Aktien kaufe ich jetzt"
    },
    {
      "title": "TESLA RUTSCHT AB! : Drei Aktien-Alternativen im E-Auto-Business",
      "teaser": "Tesla schmiert ab. Kein Problem. Die BILD-Finanz-Diva hat drei Top-Alternativen für Sie.",
      "url": "https://www.bild.de/bild-plus/geld/mein-geld/leben-und-sparen/finanz-diva-drei-top-aktien-gegen-die-tesla-misere-80168902.bild.html",
      "image_title": "Finanz-Diva: Drei Top-Aktien gegen die Tesla-Misere"
    },
    {
      "title": "Trotz Inflation! : So sparen Sie für Ihre Kinder",
      "teaser": "Wichtig, dass wir unseren Kindern möglichst FRÜH einen umsichtigen Umgang mit Geld beibringen.",
      "url": "https://www.bild.de/bild-plus/geld/mein-geld/wirtschaft/trotz-inflation-so-sparen-sie-am-besten-fuer-ihre-kinder-80164204.bild.html",
      "image_title": "Trotz Inflation! So sparen Sie am besten für Ihre Kinder"
    },
    {
      "title": "Hilfe beim Sparen : Fünf Psycho-Tricks für den Umgang mit Geld",
      "teaser": "Wie entwickeln wir ein gesundes Verhältnis zu Geld? Die Psychologin weiß, wie es geht.",
      "url": "https://www.bild.de/geld/mein-geld/leben-und-sparen/sparen-fuenf-psycho-tricks-fuer-den-umgang-mit-geld-80127506.bild.html",
      "image_title": "Sparen: Fünf Psycho-Tricks für den Umgang mit Geld"
    },
    {
      "title": "Absahnen für die Ewigkeit : Diese 12 Top-Aktien müssen Sie niemals verkaufen",
      "teaser": "Die hohe Aktien-Kunst liegt im richtigen Verkaufen. Mit diesen Aktien müssen sie sie nicht beherrschen.",
      "url": "https://www.bild.de/bild-plus/geld/mein-geld/leben-und-sparen/boerse-12-top-aktien-die-sie-niemals-verkaufen-muessen-80115548.bild.html",
      "image_title": "Börse: 12 Top-Aktien, die Sie niemals verkaufen müssen"
    },
    {
      "title": "Habeck ruft zweite Gas-Alarmstufe aus : Vier kalte Wochen wären schon zu viel",
      "teaser": "Weil Wladimir Putin die Gaslieferungen drosselt, droht Deutschland der Energienotstand.",
      "url": "https://www.bild.de/bild-plus/geld/wirtschaft/wirtschaft/angst-vor-dem-bibber-winter-wie-lange-halten-unsere-gas-reserven-80463372.bild.html",
      "image_title": "Angst vor dem Bibber-Winter: Wie lange halten unsere Gasreserven?"
    },
    {
      "title": "Rente, Auto, Hausbau : Hier gibt’s jede Menge Kohle vom Staat",
      "teaser": "Der Papierkram ist lästig, doch, wer weiß wie, kann richtig Geld vom Staat einheimsen.",
      "url": "https://www.bild.de/bild-plus/geld/wirtschaft/wirtschaft/rente-auto-hausbau-hier-gibt-es-viel-geld-vom-staat-80464204.bild.html",
      "image_title": "Rente, Auto, Hausbau: Hier gibt es viel Geld vom Staat"
    },
    {
      "title": "Wie sehr Ihre Beiträge ansteigen : So kaputt ist die Rente!",
      "teaser": "Es ist DAS Tabu-Thema der Spitzenpolitiker: die Situation der Rentenkasse!",
      "url": "https://www.bild.de/bild-plus/geld/wirtschaft/wirtschaft/historisches-versprechen-wackelt-so-kaputt-ist-die-rente-minister-heil-80471594.bild.html",
      "image_title": "Historisches Versprechen wackelt: So kaputt ist die Rente, Minister Heil!"
    },
    {
      "title": "Mehrere Tausend Euro im Jahr : Dieser Renten-Beitragsschock droht IHNEN bald",
      "teaser": "Die Rentenkasse steckt in akuter Finanznot! Wie schlimm es ist, hat die Bundesbank erre...",
      "url": "https://www.bild.de/bild-plus/geld/wirtschaft/wirtschaft/bundesbank-rentenbeitraege-bis-2040-um-bis-zu-200-euro-rauf-80456360.bild.html",
      "image_title": "Bundesbank: Rentenbeiträge bis 2040 um bis zu 200 Euro rauf!"
    },
    {
      "title": "Der Teuer-Kalender von BILD : Hier steigen bis Jahresende die Preise",
      "teaser": "Ein Ende des Teuer-Schocks ist nicht in Sicht! BILD zeigt, wo die Preise weiter rauf gehen",
      "url": "https://www.bild.de/bild-plus/geld/wirtschaft/wirtschaft/der-teuer-kalender-von-bild-hier-steigen-bis-jahresende-die-preise-80460264.bild.html",
      "image_title": "Der BILD-Teuer-Kalender: Hier steigen bis Jahresende die Preise"
    },
    {
      "title": "Wende an den Finanzmärkten : Wie sichere ich mir jetzt niedrige Zinsen für später?",
      "url": "https://www.bild.de/bild-plus/geld/wirtschaft/wirtschaft/mein-geld-kolumne-wie-sichere-ich-mir-niedrige-zinsen-79858810.bild.html",
      "image_title": "„Mein Geld“-Kolumne: Wie sichere ich mir niedrige Zinsen?"
    },
    {
      "title": "Angebotsliste auf einen Blick : Das kostet heute ein Einfamilienhaus in Deutschland",
      "teaser": "Am teuersten sind die Häuser im bayerischen Miesbach, am günstigsten im Kyffhäuserkreis.",
      "url": "https://www.bild.de/bild-plus/geld/wirtschaft/wirtschaft/auf-einen-blick-das-kostet-heute-ein-einfamilienhaus-in-deutschland-77583838.bild.html",
      "image_title": "Angebotsliste auf einen Blick: Das kostet heute ein Einfamilienhaus in Deutschland"
    },
    {
      "title": "Reicht das „Eigenkapital“? : 7 Fehler, die Sie beim Haus-Kauf vermeiden müssen!",
      "teaser": "Was sind die größten Fehler beim Immobilienkauf? Und wann gehen die Haus-Preise wieder runter? Das lesen Sie in der Mein-Geld-Kolumne.",
      "url": "https://www.bild.de/bild-plus/politik/2021/politik/hauskauf-ratgeber-das-sind-die-groessten-fehler-beim-immobilienkauf-75033944.bild.html",
      "image_title": "Reicht das „Eigenkapital“?: 7 Fehler, die Sie beim Haus-Kauf vermeiden müssen!"
    },
    {
      "title": "Trotz Niedrigzinsen : Banken plötzlich strenger bei Immobilien-Krediten!",
      "teaser": "Hilfreiche Tipps zur Immo-Finanzierung: Erfahren Sie, was sich durch Corona verändert hat – und wie Sie darauf reagieren sollten!",
      "url": "https://www.bild.de/bild-plus/politik/inland/politik-inland/corona-und-immobilien-finanzierung-kredit-zu-kriegen-ist-schwerer-geworden-71942926.bild.html",
      "image_title": "Trotz Niedrigzinsen: Banken plötzlich strenger bei Immobilien-Krediten!"
    },
    {
      "title": "Kehrtwende auf Immo-Markt : Wer eine Wohnung sucht, hat jetzt gute Chancen",
      "teaser": "Auf der Suche nach einer Immobilie sind starke Nerven wichtig. Hier könnte die Corona-Krise ausnahmsweise positive Auswirkungen haben.",
      "url": "https://www.bild.de/geld/wirtschaft/wirtschaft/coronavirus-und-immobilien-die-krise-erhoeht-chancen-auf-wunschobjekt-70525902.bild.html",
      "image_title": "Krasse Corona-Kehrtwende auf dem Immo-Markt: Wer eine Wohnung sucht, hat jetzt plötzlich gute Chancen"
    },
    {
      "title": "Keine Versicherung nach Leukämie : „Mein Krebs soll endlich gelöscht werden“",
      "url": "https://www.bild.de/bild-plus/ratgeber/2022/ratgeber/huerden-nach-krebs-miriams-leukaemie-soll-in-vergessenheit-geraten-80002382.bild.html",
      "image_title": "Hürden nach Krebs: Miriams Leukämie soll in Vergessenheit geraten"
    },
    {
      "title": "Unterhalt fürs Auto : So sparen Sie jährlich mehrere Hundert Euro",
      "teaser": "An den Spritpreisen können Sie nichts ändern, an den Unterhaltskosten für Ihr Auto schon!",
      "url": "https://www.bild.de/bild-plus/auto/auto-news/auto-news/unterhalt-fuers-auto-mit-diesen-tipps-sparen-sie-jaehrlich-mehrere-hundert-euro-80419876.bild.html",
      "image_title": "Unterhalt fürs Auto: Mit diesen Tipps sparen Sie jährlich mehrere Hundert Euro"
    },
    {
      "title": "Senior verzweifelt : „Ein Feuerteufel machte mich obdachlos!“",
      "teaser": "Durch einen Brandanschlag hat der Pfälzer Johann Noack (76) seine Wohnung verloren.",
      "url": "https://www.bild.de/regional/frankfurt/frankfurt-aktuell/senior-76-verzweifelt-ein-feuerteufel-machte-mich-obdachlos-80037994.bild.html",
      "image_title": "Senior (76) verzweifelt: „Ein Feuerteufel machte mich obdachlos!\""
    },
    {
      "title": "Sturmjahr 2021 : 165 600 Autos in Bayern beschädigt",
      "teaser": "Sturm, Hagel, Blitz und Überschwemmungen haben Bayerns Autobesitzer im vergangenen Jahr schwer getroffen",
      "url": "https://www.bild.de/regional/muenchen/muenchen-aktuell/sturmjahr-2021-165-600-autos-in-bayern-beschaedigt-79994218.bild.html",
      "image_title": "Sturmjahr 2021: 165 600 Autos in Bayern beschädigt"
    },
    {
      "title": "Neubau an der B1 : Continentale will in Dortmund hoch hinaus",
      "teaser": "Die Continentale Versicherung legte den Grundstein für ihre neue Firmenzentrale.",
      "url": "https://www.bild.de/regional/ruhrgebiet/ruhrgebiet-aktuell/neubau-direkt-an-der-b1-in-dortmund-continentale-will-hoch-hinaus-79979534.bild.html",
      "image_title": "Neubau direkt an der B1 in Dortmund: Continentale will hoch hinaus"
    },
    {
      "title": "Streit mit Versicherung : Knatsch um Kuhmist-Kraftwerk",
      "teaser": "Jahrelang stand auf dem Hof von Bernd Thies (58) eine Wunder-Maschine, die aus Sch… Geld machte.",
      "url": "https://www.bild.de/regional/hamburg/hamburg-aktuell/bauer-streitet-mit-versicherung-knatsch-um-kuhmist-kraftwerk-79959036.bild.html",
      "image_title": "Bauer streitet mit Versicherung: Knatsch um Kuhmist-Kraftwerk"
    }
  ]
}